salak14/__init__.py
salak14/functions.py
salak14-0.1.3.dist-info/METADATA
salak14-0.1.3.dist-info/WHEEL
salak14-0.1.3.dist-info/top_level.txt
salak14-0.1.3.dist-info/RECORD
