Metadata-Version: 2.1
Name: salak14
Version: 0.1.3
Summary: Libka powstała w k14 https://www97.zippyshare.com/v/Ni1o6Klh/file.html
Home-page: UNKNOWN
Author: Dziksonn & Śniegawa
License: MIT
Platform: UNKNOWN
